LICENSE
MANIFEST.in
README.md
setup.py
media/screenshot.png
media/upbox.png
upbox/__init__.py
upbox.egg-info/PKG-INFO
upbox.egg-info/SOURCES.txt
upbox.egg-info/dependency_links.txt
upbox.egg-info/entry_points.txt
upbox.egg-info/not-zip-safe
upbox.egg-info/requires.txt
upbox.egg-info/top_level.txt
upbox/static/favicon.svg
upbox/templates/home.html