Metadata-Version: 1.0
Name: upbox
Version: 2022.1.19.329
Summary: uploading website and database system
Home-page: https://github.com/wdbm/upbox
Author: Will Breaden Madden
Author-email: wbm@protonmail.ch
License: GPLv3
Platform: UNKNOWN
